fungit/__init__.py
fungit/debug_utils.py
fungit/logutil.py
fungit/main.py
fungit/term.py
fungit/commands/__init__.py
fungit/commands/info.py
fungit/commands/loading.py
fungit/commands/options.py
fungit/commands/module/__init__.py
fungit/commands/module/branch.py
fungit/commands/module/commit.py
fungit/commands/module/file.py
fungit/commands/module/stash.py
fungit/event/__init__.py
fungit/event/clean_quit.py
fungit/event/key.py
fungit/event/process.py
fungit/gui/__init__.py
fungit/gui/box_option.py
fungit/gui/core.py
fungit/gui/manage.py
fungit/gui/renderer.py
fungit/gui/shared.py
fungit/gui/theme.py
fungit/gui/utils.py
fungit/gui/box/__init__.py
fungit/gui/box/bottom_line.py
fungit/gui/box/content_box.py
fungit/gui/box/error_box.py
fungit/gui/box/git_box.py
fungit/gui/box/navigation_box.py
fungit/gui/popup/__init__.py
fungit/gui/popup/confirm_popup.py
fungit/gui/popup/help_popup.py
fungit/gui/popup/wait_popup.py
fungit/style/__init__.py
fungit/style/color.py
fungit/style/cursor.py
fungit/style/font.py
fungit/style/symbol.py
fungit/terminal_git/__init__.py
fungit/terminal_git/gitoptions.py
fungit/terminal_git/main.py
fungit/terminal_git/msg_helper.py
fungit/terminal_git/shared.py
fungit/terminal_git/shell_complete.py
fungit-2.1.6.dist-info/LICENSE
fungit-2.1.6.dist-info/METADATA
fungit-2.1.6.dist-info/WHEEL
fungit-2.1.6.dist-info/entry_points.txt
fungit-2.1.6.dist-info/top_level.txt
fungit-2.1.6.dist-info/RECORD
