Metadata-Version: 2.1
Name: fungit
Version: 2.1.6
Summary: Simple terminal tool of Git.
Home-page: https://github.com/zlj-zz/fungit.git
Author: Zachary Zhang
Author-email: zlj19971222@outlook.com
License: UNKNOWN
Platform: UNKNOWN
Classifier: Programming Language :: Python :: 3.7
Classifier: Programming Language :: Python :: 3.8
Classifier: Programming Language :: Python :: 3.9
Classifier: Intended Audience :: Developers
Classifier: License :: OSI Approved :: MIT License
Classifier: Operating System :: OS Independent
Requires-Python: >=3.7
